LICENSE
README.md
pyproject.toml
setup.py
notifyhub/__init__.py
notifyhub.egg-info/PKG-INFO
notifyhub.egg-info/SOURCES.txt
notifyhub.egg-info/dependency_links.txt
notifyhub.egg-info/requires.txt
notifyhub.egg-info/top_level.txt
notifyhub/bots/__init__.py
notifyhub/bots/discordbot.py
notifyhub/bots/telegrambot.py