Metadata-Version: 2.1
Name: notifyhub
Version: 0.0.5
Summary: Notification on instant messaging platforms
Home-page: https://github.com/Kennard123661/notifyhub
Author: Kennard Ng
Author-email: kennard.ng.pool.hua@gmail.com
License: UNKNOWN
Platform: UNKNOWN
Classifier: Programming Language :: Python :: 3
Classifier: License :: OSI Approved :: MIT License
Classifier: Operating System :: OS Independent
Requires-Python: >=3.6
License-File: LICENSE
